MANIFEST.in
README.md
setup.py
embeddix/__init__.py
embeddix/main.py
embeddix.egg-info/PKG-INFO
embeddix.egg-info/SOURCES.txt
embeddix.egg-info/dependency_links.txt
embeddix.egg-info/entry_points.txt
embeddix.egg-info/not-zip-safe
embeddix.egg-info/requires.txt
embeddix.egg-info/top_level.txt
embeddix/core/__init__.py
embeddix/core/converter.py
embeddix/core/evaluator.py
embeddix/core/extractor.py
embeddix/core/reducer.py
embeddix/exceptions/__init__.py
embeddix/exceptions/method.py
embeddix/exceptions/parameter.py
embeddix/logging/__init__.py
embeddix/logging/logging.yml
embeddix/resources/.DS_Store
embeddix/resources/MEN_dataset_natural_form_full
embeddix/resources/STS2012.full.tokenized.lower.txt
embeddix/resources/STS2012.full.txt
embeddix/resources/STS2014.OnWN.tokenized.lower.txt
embeddix/resources/STS2014.OnWN.txt
embeddix/resources/STS2014.headlines.tokenized.lower.txt
embeddix/resources/SimLex-999.txt
embeddix/resources/SimVerb-3500.txt
embeddix/resources/WS353.combined.txt
embeddix/resources/__init__.py
embeddix/resources/ap.csv
embeddix/resources/battig.csv
embeddix/resources/essli-2008.csv
embeddix/utils/__init__.py
embeddix/utils/config.py
embeddix/utils/data.py
embeddix/utils/files.py
embeddix/utils/immutables.py
embeddix/utils/metrix.py
embeddix/utils/stats.py