Metadata-Version: 2.1
Name: embeddix
Version: 1.16.0
Summary: A general purpose toolkit for word embeddings
Home-page: https://github.com/akb89/embeddix
Author:  Alexandre Kabbach
Author-email: akb@3azouz.net
License: MIT
Download-URL: https://github.com/akb89/embeddix
Keywords: word embeddings,toolkit,conversion,nlp
Platform: any
Classifier: Development Status :: 5 - Production/Stable
Classifier: Environment :: Web Environment
Classifier: Intended Audience :: Developers
Classifier: Intended Audience :: Education
Classifier: Intended Audience :: Science/Research
Classifier: License :: OSI Approved :: MIT License
Classifier: Natural Language :: English
Classifier: Operating System :: OS Independent
Classifier: Programming Language :: Python :: 3.6
Classifier: Programming Language :: Python :: 3.7
Classifier: Programming Language :: Python :: 3.8
Classifier: Topic :: Scientific/Engineering :: Artificial Intelligence
Classifier: Topic :: Software Development :: Libraries :: Python Modules
